car_framework/__init__.py
car_framework/app.py
car_framework/base_import.py
car_framework/car_service.py
car_framework/communicator.py
car_framework/context.py
car_framework/data_handler.py
car_framework/extension.py
car_framework/full_import.py
car_framework/inc_import.py
car_framework/server_access.py
car_framework/util.py
car_connector_framework-4.0.2.dist-info/LICENSE
car_connector_framework-4.0.2.dist-info/LICENSE.txt
car_connector_framework-4.0.2.dist-info/METADATA
car_connector_framework-4.0.2.dist-info/WHEEL
car_connector_framework-4.0.2.dist-info/top_level.txt
car_connector_framework-4.0.2.dist-info/RECORD
