Metadata-Version: 2.1
Name: car-connector-framework
Version: 4.0.2
Summary: CAR service connector framework
Home-page: https://github.com/IBM/cp4s-car-connector-framework
Author: IBM
Author-email: 
License: Apache License 2.0
Platform: Any
Classifier: Programming Language :: Python :: 3.6
Classifier: License :: OSI Approved :: Apache Software License
Classifier: Operating System :: OS Independent
Requires-Python: >=3.6
License-File: LICENSE
License-File: LICENSE.txt
Requires-Dist: python-json-logger ==2.0.7
Requires-Dist: jwcrypto >=1.4.2
Requires-Dist: urllib3 ==1.26.19
Requires-Dist: jschon ==0.8.5
Requires-Dist: requests >=2.24.0
